{
  "lessonId": "lesson_001",
  "title": "Conversaci칩n en una cafeter칤a",
  "description": "Simulaci칩n de una conversaci칩n entre tres personas en una cafeter칤a para practicar saludos y presentaciones.",
  "participants": [
    { "id": "1", "name": "Ana" },
    { "id": "2", "name": "Luis" },
    { "id": "3", "name": "Marta" }
  ],
  "content": [
    {
      "type": "dialogue",
      "id": "dialogue_1",
      "speakerId": "1",
      "text": "_____, 쯖칩mo est치s?"
    },
    {
      "id": 1,
      "type": "multiple_choice",
      "title": "Selecciona la respuesta correcta",
      "description": "",
      "instructions": "",
      "question": "쯈u칠 se침a deber칤a utilizar Ana para saludar a Luis?\n\n游뗿",
      "options": [
          "imagen1",
          "imagen2",
          "imagen3",
          "imagen4"
      ],
      "correct_option": "imagen2",
      "max_attempts": 2,
      "feedback": {
          "correct": "춰Correcto! Sigamos",
          "incorrect": "Respuesta incorrecta. Intenta de nuevo.",
          "completed": "Has completado la pregunta."
      }
    },
    {
      "type": "dialogue",
      "id": "dialogue_2",
      "speakerId": "2",
      "text": "Hola, Ana. Muy bien, gracias. 쯏 t칰?"
    },
    {
      "type": "dialogue",
      "id": "dialogue_3",
      "speakerId": "3",
      "text": "Hola a ambos. 쯇uedo unirme?"
    },
    {
      "type": "dialogue",
      "id": "dialogue_4",
      "speakerId": "1",
      "text": "Claro, adelante. Estoy practicando una nueva se침al. 쯈uieres intentarlo conmigo?"
    },
    {
      "id": 2,
      "type": "sign_detection",
      "title": "Realiza la se침a correcta",
      "description": "Haz la se침a para decir 'Hola'. Imagen de la se침a: img.jpg", 
      "instructions": "Realiza la se침a para 'Hola' frente a la c치mara. El sistema te indicar치 si es correcta.",
      "sign_to_detect": 0,
      "correct": "춰Bien hecho! Has realizado la se침a de 'Hola' correctamente."
    },
    {
      "type": "dialogue",
      "id": "dialogue_4",
      "speakerId": "1",
      "text": "Claro, adelante. Estoy practicando una nueva se침al. 쯈uieres intentarlo conmigo?"
    }
  ]
}
